LigralPy/__init__.py
LigralPy/__main__.py
LigralPy/config.py
LigralPy/run_ligral.py
LigralPy/demos/one-order-system.json
LigralPy/demos/second-order-system.json
LigralPy/demos/simple-route.json
LigralPy/demos/spring-damp.json
LigralPy/demos/use-simple-route.json
LigralPy/models/exceptions.py
LigralPy/models/flowchart_settings.py
LigralPy/models/group.py
LigralPy/nodes/__init__.py
LigralPy/nodes/appearance_manager.py
LigralPy/nodes/appearances.json
LigralPy/nodes/external_nodes.py
LigralPy/nodes/node.py
LigralPy/nodes/nodes_mgr.py
LigralPy/nodes/external_nodejsons/UDPListenerDefault.mdl.json
LigralPy/nodes/external_nodejsons/UDPSenderDefault.mdl.json
LigralPy/nodes/nodejsons/Abs.mdl.json
LigralPy/nodes/nodejsons/Acos.mdl.json
LigralPy/nodes/nodejsons/Acosh.mdl.json
LigralPy/nodes/nodejsons/Add.mdl.json
LigralPy/nodes/nodejsons/Asin.mdl.json
LigralPy/nodes/nodejsons/Asinh.mdl.json
LigralPy/nodes/nodejsons/Atan.mdl.json
LigralPy/nodes/nodejsons/Atan2.mdl.json
LigralPy/nodes/nodejsons/Atanh.mdl.json
LigralPy/nodes/nodejsons/BoundedIntegrator.mdl.json
LigralPy/nodes/nodejsons/Clock.mdl.json
LigralPy/nodes/nodejsons/Constant.mdl.json
LigralPy/nodes/nodejsons/Cos.mdl.json
LigralPy/nodes/nodejsons/Cosh.mdl.json
LigralPy/nodes/nodejsons/Cot.mdl.json
LigralPy/nodes/nodejsons/Cross.mdl.json
LigralPy/nodes/nodejsons/Csc.mdl.json
LigralPy/nodes/nodejsons/Deadzone.mdl.json
LigralPy/nodes/nodejsons/Div.mdl.json
LigralPy/nodes/nodejsons/DotDiv.mdl.json
LigralPy/nodes/nodejsons/DotMul.mdl.json
LigralPy/nodes/nodejsons/DotPow.mdl.json
LigralPy/nodes/nodejsons/Equal.mdl.json
LigralPy/nodes/nodejsons/EqualToZero.mdl.json
LigralPy/nodes/nodejsons/Exp.mdl.json
LigralPy/nodes/nodejsons/Gain.mdl.json
LigralPy/nodes/nodejsons/HSplit.mdl.json
LigralPy/nodes/nodejsons/HStack.mdl.json
LigralPy/nodes/nodejsons/InputMarker.mdl.json
LigralPy/nodes/nodejsons/Integrator.mdl.json
LigralPy/nodes/nodejsons/Interpolation.mdl.json
LigralPy/nodes/nodejsons/Interpolation2D.mdl.json
LigralPy-0.3.3.dist-info/LICENSE
LigralPy-0.3.3.dist-info/METADATA
LigralPy-0.3.3.dist-info/WHEEL
LigralPy-0.3.3.dist-info/top_level.txt
LigralPy-0.3.3.dist-info/RECORD
