Metadata-Version: 2.1
Name: LigralPy
Version: 0.3.3
Summary: Python interface to Ligral.
Home-page: UNKNOWN
Author: Zhanyi Hou
Author-email: 
License: BSD 3
Platform: UNKNOWN
Classifier: Development Status :: 4 - Beta
Classifier: Intended Audience :: Science/Research
Classifier: License :: OSI Approved :: BSD License
Classifier: Natural Language :: English
Classifier: Operating System :: Unix
Classifier: Operating System :: Microsoft :: Windows
Classifier: Programming Language :: Python :: 3
Classifier: Topic :: Scientific/Engineering
Requires-Python: >=3.5
License-File: LICENSE
Requires-Dist: chardet
Requires-Dist: numpy
Requires-Dist: pandas
Requires-Dist: matplotlib
Requires-Dist: openpyxl
Requires-Dist: appdirs
Requires-Dist: flask
Requires-Dist: flask-sock
